TensorflowHeKerasYingyongKaifaRumenChuyiFix1/README.md
TensorflowHeKerasYingyongKaifaRumenChuyiFix1/__init__.py
TensorflowHeKerasYingyongKaifaRumenChuyiFix1/__main__.py
TensorflowHeKerasYingyongKaifaRumenChuyiFix1/file.epub
TensorflowHeKerasYingyongKaifaRumenChuyiFix1/index.html
TensorflowHeKerasYingyongKaifaRumenChuyiFix1/css/__init__.py
TensorflowHeKerasYingyongKaifaRumenChuyiFix1/css/annotations.css
TensorflowHeKerasYingyongKaifaRumenChuyiFix1/css/main.css
TensorflowHeKerasYingyongKaifaRumenChuyiFix1/css/normalize.css
TensorflowHeKerasYingyongKaifaRumenChuyiFix1/css/popup.css
TensorflowHeKerasYingyongKaifaRumenChuyiFix1/font/__init__.py
TensorflowHeKerasYingyongKaifaRumenChuyiFix1/font/fontello.eot
TensorflowHeKerasYingyongKaifaRumenChuyiFix1/font/fontello.svg
TensorflowHeKerasYingyongKaifaRumenChuyiFix1/font/fontello.ttf
TensorflowHeKerasYingyongKaifaRumenChuyiFix1/font/fontello.woff
TensorflowHeKerasYingyongKaifaRumenChuyiFix1/img/__init__.py
TensorflowHeKerasYingyongKaifaRumenChuyiFix1/img/annotator-glyph-sprite.png
TensorflowHeKerasYingyongKaifaRumenChuyiFix1/img/annotator-icon-sprite.png
TensorflowHeKerasYingyongKaifaRumenChuyiFix1/img/apple-touch-icon.png
TensorflowHeKerasYingyongKaifaRumenChuyiFix1/img/cancelfullscreen.png
TensorflowHeKerasYingyongKaifaRumenChuyiFix1/img/close.png
TensorflowHeKerasYingyongKaifaRumenChuyiFix1/img/fullscreen.png
TensorflowHeKerasYingyongKaifaRumenChuyiFix1/img/loader.gif
TensorflowHeKerasYingyongKaifaRumenChuyiFix1/img/menu-icon.png
TensorflowHeKerasYingyongKaifaRumenChuyiFix1/img/save.png
TensorflowHeKerasYingyongKaifaRumenChuyiFix1/img/saved.png
TensorflowHeKerasYingyongKaifaRumenChuyiFix1/img/settings-s.png
TensorflowHeKerasYingyongKaifaRumenChuyiFix1/img/settings.png
TensorflowHeKerasYingyongKaifaRumenChuyiFix1/img/star.png
TensorflowHeKerasYingyongKaifaRumenChuyiFix1/js/__init__.py
TensorflowHeKerasYingyongKaifaRumenChuyiFix1/js/epub.js
TensorflowHeKerasYingyongKaifaRumenChuyiFix1/js/epub.min.js
tensorflow_he_keras_yingyong_kaifa_rumen_chuyi_fix1-2025.3.25.0.dist-info/METADATA
tensorflow_he_keras_yingyong_kaifa_rumen_chuyi_fix1-2025.3.25.0.dist-info/WHEEL
tensorflow_he_keras_yingyong_kaifa_rumen_chuyi_fix1-2025.3.25.0.dist-info/entry_points.txt
tensorflow_he_keras_yingyong_kaifa_rumen_chuyi_fix1-2025.3.25.0.dist-info/top_level.txt
tensorflow_he_keras_yingyong_kaifa_rumen_chuyi_fix1-2025.3.25.0.dist-info/RECORD
